{"type": "Feature", "id": 12513019, "properties": {"woe:id": 12513019, "woe:parent_id": 1963092, "woe:name": "Tskhinvali South Airport", "woe:placetype": 14, "woe:placetype_name": "Airport", "woe:lang": "ENG", "iso:country": "GE", "meta:provider": ["geoplanet:7.3.1", "geoplanet:7.3.2", "geoplanet:7.4.0", "geoplanet:7.4.1", "geoplanet:7.5.1", "geoplanet:7.5.2", "geoplanet:7.6.0", "geoplanet:7.8.1", "geoplanet:7.9.0", "geoplanet:7.10.0", "geoplanet:8.0.0", "woeplanet:8.0.0"], "meta:indexed": "2020-08-20T20:56:33.805584", "meta:updated": "2020-08-22T02:53:20.448919", "woe:hierarchy": {"continent": 24865671, "country": 23424823, "town": 0, "planet": 1, "county": 0, "suburb": 0, "state": 20070368, "region": 0, "localadmin": 0}, "woe:timezone_id": 28350858, "woe:hash": "szrpxtfregr8", "woe:centroid": [43.926601, 42.1325], "geom:latitude": 42.1325, "geom:longitude": 43.926601, "geom:hash": "szrpxtfregr8", "woe:latitude": 42.1325, "geom:centroid": [43.926601, 42.1325], "woe:longitude": 43.926601, "woe:repo": "woeplanet-airport-ge"}, "geometry": {"coordinates": [43.926601, 42.1325], "type": "Point"}}