{"type": "Feature", "id": 12513012, "properties": {"woe:id": 12513012, "woe:parent_id": 1962539, "woe:name": "Skmtredia East Airport", "woe:placetype": 14, "woe:placetype_name": "Airport", "woe:lang": "ENG", "iso:country": "GE", "meta:provider": ["geoplanet:7.3.1", "geoplanet:7.3.2", "geoplanet:7.4.0", "geoplanet:7.4.1", "geoplanet:7.5.1", "geoplanet:7.5.2", "geoplanet:7.6.0", "geoplanet:7.8.1", "geoplanet:7.9.0", "geoplanet:7.10.0", "geoplanet:8.0.0", "woeplanet:8.0.0"], "meta:indexed": "2020-08-20T20:56:33.799781", "meta:updated": "2020-08-22T02:53:20.445586", "woe:hierarchy": {"continent": 24865671, "country": 23424823, "town": 0, "planet": 1, "county": 0, "suburb": 0, "state": 20070393, "region": 0, "localadmin": 0}, "woe:timezone_id": 28350858, "woe:hash": "szqpyytn044w", "woe:centroid": [42.491001, 42.180302], "geom:latitude": 42.180302, "geom:longitude": 42.491001, "geom:hash": "szqpyytn044w", "woe:latitude": 42.180302, "geom:centroid": [42.491001, 42.180302], "woe:longitude": 42.491001, "woe:repo": "woeplanet-airport-ge"}, "geometry": {"coordinates": [42.491001, 42.180302], "type": "Point"}}