{"type": "Feature", "id": 12513021, "properties": {"woe:id": 12513021, "woe:parent_id": 1963653, "woe:name": "Zugdidi Airport", "woe:placetype": 14, "woe:placetype_name": "Airport", "woe:lang": "ENG", "iso:country": "GE", "meta:provider": ["geoplanet:7.3.1", "geoplanet:7.3.2", "geoplanet:7.4.0", "geoplanet:7.4.1", "geoplanet:7.5.1", "geoplanet:7.5.2", "geoplanet:7.6.0", "geoplanet:7.8.1", "geoplanet:7.9.0", "geoplanet:7.10.0", "geoplanet:8.0.0", "woeplanet:8.0.0"], "meta:indexed": "2020-08-20T20:56:33.807498", "meta:updated": "2020-08-22T02:53:20.449843", "woe:hierarchy": {"continent": 24865671, "country": 23424823, "town": 0, "planet": 1, "county": 0, "suburb": 0, "state": 20070410, "region": 0, "localadmin": 0}, "woe:timezone_id": 28350858, "woe:hash": "szt9xx2udmrb", "woe:centroid": [41.815102, 42.491798], "geom:latitude": 42.491798, "geom:longitude": 41.815102, "geom:hash": "szt9xx2udmrb", "woe:latitude": 42.491798, "geom:centroid": [41.815102, 42.491798], "woe:longitude": 41.815102, "woe:repo": "woeplanet-airport-ge"}, "geometry": {"coordinates": [41.815102, 42.491798], "type": "Point"}}