{"type": "Feature", "id": 12513015, "geometry": {"type": "Point", "coordinates": [44.955601, 41.6716]}, "properties": {"woe:id": 12513015, "woe:parent_id": 1963037, "woe:name": "Tbilisi-Noyo Alekseyevka Airport", "woe:placetype": 14, "woe:placetype_name": "Airport", "woe:lang": "ENG", "iso:country": "GE", "meta:provider": ["geoplanet:7.3.1", "geoplanet:7.3.2", "geoplanet:7.4.0", "geoplanet:7.4.1", "geoplanet:7.5.1", "geoplanet:7.5.2", "geoplanet:7.6.0", "geoplanet:7.8.1", "geoplanet:7.9.0", "geoplanet:7.10.0", "geoplanet:8.0.0", "woeplanet:8.0.0"], "meta:indexed": "2020-08-20T20:56:33.802189", "woe:alias_ENG_V": ["TBS Airport", "TBS", "Tbilisi-Noyo Alekseyevka"], "meta:updated": "2020-10-14T10:59:56.806482", "woe:hierarchy": {"continent": 24865671, "country": 23424823, "town": 0, "planet": 1, "county": 0, "suburb": 0, "state": 20070408, "region": 0, "localadmin": 0}, "woe:timezone_id": 28350858, "woe:hash": "szrvnfpdtmm8", "woe:centroid": [44.955601, 41.6716], "geom:latitude": 41.6716, "geom:longitude": 44.955601, "geom:hash": "szrvnfpdtmm8", "woe:latitude": 41.6716, "geom:centroid": [44.955601, 41.6716], "woe:longitude": 44.955601, "woe:repo": "woeplanet-airport-ge", "geom:area": 0.0, "woe:scale": 19}}